meshemy/__init__.py
meshemy/blender/__init__.py
meshemy/blender/constant.py
meshemy/blender/shortcut/__init__.py
meshemy/blender/shortcut/io.py
meshemy/blender/shortcut/select.py
meshemy/blender/utils.py
meshemy/blender/workflows.py
meshemy/cookbook/__init__.py
meshemy/cookbook/base.py
meshemy/cookbook/blender.py
meshemy/cookbook/open3d.py
meshemy/cookbook/trimesh.py
meshemy/utility/__init__.py
meshemy/utility/exception.py
meshemy/utility/io.py
meshemy-2.0.0.dist-info/LICENSE.md
meshemy-2.0.0.dist-info/METADATA
meshemy-2.0.0.dist-info/WHEEL
meshemy-2.0.0.dist-info/RECORD
