Metadata-Version: 2.1
Name: meshemy
Version: 2.0.0
Summary: Developer friendly suite for manipulating mesh
License: BSD-4
Author: caniko
Author-email: canhtart@gmail.com
Requires-Python: >=3.10,<3.11.0
Classifier: License :: Other/Proprietary License
Classifier: Programming Language :: Python :: 3
Classifier: Programming Language :: Python :: 3.10
Provides-Extra: blender
Provides-Extra: full
Provides-Extra: open3d
Provides-Extra: trimesh
Requires-Dist: bpy (>=3.4.0,<4.0.0) ; extra == "full" or extra == "blender"
Requires-Dist: numpy (<1.25.0)
Requires-Dist: open3d-cpu (>=0.17.0,<0.18.0) ; extra == "full" or extra == "open3d"
Requires-Dist: ordered-set (>=4.1.0,<5.0.0)
Requires-Dist: pydantic (>=2.0,<3.0)
Requires-Dist: pydantic-numpy
Requires-Dist: pymeshfix (>=0.16.2,<0.17.0)
Requires-Dist: trimesh (>=3.20.2,<4.0.0) ; extra == "full" or extra == "trimesh"
